datalight/__init__.py
datalight/common.py
datalight/main.py
datalight/zenodo.py
datalight/zenodo_metadata.py
datalight-0.9.1.dist-info/AUTHORS.rst
datalight-0.9.1.dist-info/LICENSE
datalight-0.9.1.dist-info/METADATA
datalight-0.9.1.dist-info/WHEEL
datalight-0.9.1.dist-info/top_level.txt
datalight-0.9.1.dist-info/RECORD
