Metadata-Version: 2.1
Name: datalight
Version: 0.9.1
Summary: Data uploader to Zenodo repository
Home-page: https://github.com/LightForm-group/datalight
Author: Peter Crowther
Author-email: peter.crowther-3@manchester.ac.uk
License: MIT
Platform: UNKNOWN
License-File: LICENSE
License-File: AUTHORS.rst
Requires-Dist: requests
Requires-Dist: PyYaml (>=5.1)
Requires-Dist: jsonschema
Requires-Dist: PyQt5
